Workbook

Sheet Read Me
A1: GovCon Accounting Starter Sheet
A2: A free tool from GovCon Lab — govconlab.com
A5: What this is | B5: A lightweight starting point for tracking income, expenses, and basic job costing as a federal contractor — before you need a full accounting system or DCAA-compliant setup.
A6: Who it's for | B6: Small businesses just starting to win federal or GovCon work who need simple, organized records for tax time, cash flow visibility, and early job costing.
A7: Tabs in this workbook
A8: 1. Income & Expense Tracker | B8: Log every transaction, categorized, with running totals by month.
A9: 2. Job Costing by Contract | B9: Track direct costs (labor, materials, other direct costs) against each contract/CLIN so you know your real margin.
A10: 3. Indirect Rate Calculator (Simple) | B10: A simplified overhead/G&A rate calculator — a starting point, not a DCAA-compliant rate structure.
A11: 4. Monthly Summary | B11: Auto-calculated income, expenses, and net profit by month, pulled from the Income & Expense Tracker.
A12: How to use it | B12: Enter data only in the yellow-highlighted example rows' columns — replace the example values, then continue in the rows below. Formulas are already built into the totals — don't overwrite them.
A13: A note on limits | B13: This is a starting point for organizing your own records, not a substitute for a bookkeeper, CPA, or DCAA-compliant accounting system once you're pursuing cost-reimbursement contracts. As your GovCon revenue grows, GovCon Lab's full Accounting Dashboard (icrestiq.github.io/govcon-accounting) adds automated bank import, indirect rate pools, and reporting built specifically for small GovCon contractors.
A15: Want more? | B15: Join GovCon Lab at govconlab.com for the full accounting dashboard, proposal tools, and community support.

Sheet Income & Expense Tracker
A1: Income & Expense Tracker
A2: Log every transaction. Use the Category column consistently — it feeds the Monthly Summary tab.
A4: Date | B4: Description | C4: Contract / Job # | D4: Category | E4: Type (Income/Expense) | F4: Amount | G4: Notes
A5: 2026-01-15 | B5: DLA CLIN 0001 payment received | C5: SPE4A6-26-D-0012 | D5: Contract Revenue | E5: Income | F5: 4250 | G5: Net 30 paid on time
A6: 2026-01-18 | B6: Shop supplies — fasteners | C6: SPE4A6-26-D-0012 | D6: Materials/COGS | E6: Expense | F6: -186.4 | G6: Vendor: ABC Supply
A62: TOTAL INCOME | F62: =SUMIF(E5:E60,"Income",F5:F60) -> 4250
A63: TOTAL EXPENSES | F63: =SUMIF(E5:E60,"Expense",F5:F60) -> -186.4
A64: NET | F64: =F62+F63 -> 4063.6

Sheet Job Costing by Contract
A1: Job Costing by Contract
A2: Track direct costs against each contract so you know your real margin — not just cash in the door.
A4: Contract / Job # | B4: Contract Value | C4: Direct Labor | D4: Materials | E4: Subcontractor | F4: Other Direct Costs | G4: Total Direct Cost | H4: Margin ($) / Margin (%)
A5: SPE4A6-26-D-0012 | B5: 42500 | C5: 12000 | D5: 18600 | E5: 0 | F5: 950 | G5: =SUM(C5:F5) -> 31550 | H5: =(B5-G5)&" / "&TEXT((B5-G5)/B5,"0.0%") -> 10950 / 25.8%
G6: =SUM(C6:F6) -> 0 | H6: =IF(B6=0,"",(B6-G6)&" / "&TEXT((B6-G6)/B6,"0.0%"))
G7: =SUM(C7:F7) -> 0 | H7: =IF(B7=0,"",(B7-G7)&" / "&TEXT((B7-G7)/B7,"0.0%"))
G8: =SUM(C8:F8) -> 0 | H8: =IF(B8=0,"",(B8-G8)&" / "&TEXT((B8-G8)/B8,"0.0%"))
G9: =SUM(C9:F9) -> 0 | H9: =IF(B9=0,"",(B9-G9)&" / "&TEXT((B9-G9)/B9,"0.0%"))
G10: =SUM(C10:F10) -> 0 | H10: =IF(B10=0,"",(B10-G10)&" / "&TEXT((B10-G10)/B10,"0.0%"))
G11: =SUM(C11:F11) -> 0 | H11: =IF(B11=0,"",(B11-G11)&" / "&TEXT((B11-G11)/B11,"0.0%"))
G12: =SUM(C12:F12) -> 0 | H12: =IF(B12=0,"",(B12-G12)&" / "&TEXT((B12-G12)/B12,"0.0%"))
G13: =SUM(C13:F13) -> 0 | H13: =IF(B13=0,"",(B13-G13)&" / "&TEXT((B13-G13)/B13,"0.0%"))
G14: =SUM(C14:F14) -> 0 | H14: =IF(B14=0,"",(B14-G14)&" / "&TEXT((B14-G14)/B14,"0.0%"))
G15: =SUM(C15:F15) -> 0 | H15: =IF(B15=0,"",(B15-G15)&" / "&TEXT((B15-G15)/B15,"0.0%"))
G16: =SUM(C16:F16) -> 0 | H16: =IF(B16=0,"",(B16-G16)&" / "&TEXT((B16-G16)/B16,"0.0%"))
G17: =SUM(C17:F17) -> 0 | H17: =IF(B17=0,"",(B17-G17)&" / "&TEXT((B17-G17)/B17,"0.0%"))
... G30: =SUM(C30:F30) -> 0 | H30: =IF(B30=0,"",(B30-G30)&" / "&TEXT((B30-G30)/B30,"0.0%"))
A32: Note: Margin % assumes Contract Value is fixed-price. For cost-reimbursement contracts, compare Total Direct Cost against your funded ceiling instead.

Sheet Indirect Rate Calculator
A1: Indirect Rate Calculator (Simplified)
A2: A starting point for understanding your overhead rate — not a DCAA-compliant rate structure.
A4: Input | B4: Amount | C4: Description
A5: Annual Indirect (Overhead) Costs | B5: 45000 | C5: Rent, utilities, admin salaries, insurance, software, etc.
A6: Annual Direct Labor Cost | B6: 150000 | C6: Total wages paid for work directly performed on contracts.
A7: Indirect Rate (%) | B7: =IFERROR(B5/B6,"") -> 0.3 | C7: Calculated: Indirect Costs ÷ Direct Labor. Apply this rate to future direct labor estimates when pricing new work.
A9: Example: pricing a new job
A10: Estimated Direct Labor for New Job | B10: 10000
A11: Applied Indirect Cost | B11: =B10*B7 -> 3000
A12: Total Estimated Cost | B12: =B10+B11 -> 13000
A14: Yellow cells are inputs — edit those. Everything else calculates automatically.

Sheet Monthly Summary
A1: Monthly Summary
A2: Auto-calculated from the Income & Expense Tracker tab using each transaction's Date.
A4: Month | B4: Income | C4: Expenses | D4: Net Profit
A5: 2026-01 | B5: =SUMPRODUCT((TEXT('Income & Expense Tracker'!$A$5:$A$60,"yyyy-mm")=A5)*('Income & Expense Tracker'!$E$5:$E$60="Income")*'Income & Expense Tracker'!$F$5:$F$60) -> 4250 | C5: =SUMPRODUCT((TEXT('Income & Expense Tracker'!$A$5:$A$60,"yyyy-mm")=A5)*('Income & Expense Tracker'!$E$5:$E$60="Expense")*'Income & Expense Tracker'!$F$5:$F$60) -> -186.4 | D5: =B5+C5 -> 4063.6
A6: 2026-02 | B6: =SUMPRODUCT((TEXT('Income & Expense Tracker'!$A$5:$A$60,"yyyy-mm")=A6)*('Income & Expense Tracker'!$E$5:$E$60="Income")*'Income & Expense Tracker'!$F$5:$F$60) -> 0 | C6: =SUMPRODUCT((TEXT('Income & Expense Tracker'!$A$5:$A$60,"yyyy-mm")=A6)*('Income & Expense Tracker'!$E$5:$E$60="Expense")*'Income & Expense Tracker'!$F$5:$F$60) -> 0 | D6: =B6+C6 -> 0
A7: 2026-03 | B7: =SUMPRODUCT((TEXT('Income & Expense Tracker'!$A$5:$A$60,"yyyy-mm")=A7)*('Income & Expense Tracker'!$E$5:$E$60="Income")*'Income & Expense Tracker'!$F$5:$F$60) -> 0 | C7: =SUMPRODUCT((TEXT('Income & Expense Tracker'!$A$5:$A$60,"yyyy-mm")=A7)*('Income & Expense Tracker'!$E$5:$E$60="Expense")*'Income & Expense Tracker'!$F$5:$F$60) -> 0 | D7: =B7+C7 -> 0
A8: 2026-04 | B8: =SUMPRODUCT((TEXT('Income & Expense Tracker'!$A$5:$A$60,"yyyy-mm")=A8)*('Income & Expense Tracker'!$E$5:$E$60="Income")*'Income & Expense Tracker'!$F$5:$F$60) -> 0 | C8: =SUMPRODUCT((TEXT('Income & Expense Tracker'!$A$5:$A$60,"yyyy-mm")=A8)*('Income & Expense Tracker'!$E$5:$E$60="Expense")*'Income & Expense Tracker'!$F$5:$F$60) -> 0 | D8: =B8+C8 -> 0
A9: 2026-05 | B9: =SUMPRODUCT((TEXT('Income & Expense Tracker'!$A$5:$A$60,"yyyy-mm")=A9)*('Income & Expense Tracker'!$E$5:$E$60="Income")*'Income & Expense Tracker'!$F$5:$F$60) -> 0 | C9: =SUMPRODUCT((TEXT('Income & Expense Tracker'!$A$5:$A$60,"yyyy-mm")=A9)*('Income & Expense Tracker'!$E$5:$E$60="Expense")*'Income & Expense Tracker'!$F$5:$F$60) -> 0 | D9: =B9+C9 -> 0
A10: 2026-06 | B10: =SUMPRODUCT((TEXT('Income & Expense Tracker'!$A$5:$A$60,"yyyy-mm")=A10)*('Income & Expense Tracker'!$E$5:$E$60="Income")*'Income & Expense Tracker'!$F$5:$F$60) -> 0 | C10: =SUMPRODUCT((TEXT('Income & Expense Tracker'!$A$5:$A$60,"yyyy-mm")=A10)*('Income & Expense Tracker'!$E$5:$E$60="Expense")*'Income & Expense Tracker'!$F$5:$F$60) -> 0 | D10: =B10+C10 -> 0
A11: 2026-07 | B11: =SUMPRODUCT((TEXT('Income & Expense Tracker'!$A$5:$A$60,"yyyy-mm")=A11)*('Income & Expense Tracker'!$E$5:$E$60="Income")*'Income & Expense Tracker'!$F$5:$F$60) -> 0 | C11: =SUMPRODUCT((TEXT('Income & Expense Tracker'!$A$5:$A$60,"yyyy-mm")=A11)*('Income & Expense Tracker'!$E$5:$E$60="Expense")*'Income & Expense Tracker'!$F$5:$F$60) -> 0 | D11: =B11+C11 -> 0
A12: 2026-08 | B12: =SUMPRODUCT((TEXT('Income & Expense Tracker'!$A$5:$A$60,"yyyy-mm")=A12)*('Income & Expense Tracker'!$E$5:$E$60="Income")*'Income & Expense Tracker'!$F$5:$F$60) -> 0 | C12: =SUMPRODUCT((TEXT('Income & Expense Tracker'!$A$5:$A$60,"yyyy-mm")=A12)*('Income & Expense Tracker'!$E$5:$E$60="Expense")*'Income & Expense Tracker'!$F$5:$F$60) -> 0 | D12: =B12+C12 -> 0
A13: 2026-09 | B13: =SUMPRODUCT((TEXT('Income & Expense Tracker'!$A$5:$A$60,"yyyy-mm")=A13)*('Income & Expense Tracker'!$E$5:$E$60="Income")*'Income & Expense Tracker'!$F$5:$F$60) -> 0 | C13: =SUMPRODUCT((TEXT('Income & Expense Tracker'!$A$5:$A$60,"yyyy-mm")=A13)*('Income & Expense Tracker'!$E$5:$E$60="Expense")*'Income & Expense Tracker'!$F$5:$F$60) -> 0 | D13: =B13+C13 -> 0
A14: 2026-10 | B14: =SUMPRODUCT((TEXT('Income & Expense Tracker'!$A$5:$A$60,"yyyy-mm")=A14)*('Income & Expense Tracker'!$E$5:$E$60="Income")*'Income & Expense Tracker'!$F$5:$F$60) -> 0 | C14: =SUMPRODUCT((TEXT('Income & Expense Tracker'!$A$5:$A$60,"yyyy-mm")=A14)*('Income & Expense Tracker'!$E$5:$E$60="Expense")*'Income & Expense Tracker'!$F$5:$F$60) -> 0 | D14: =B14+C14 -> 0
A15: 2026-11 | B15: =SUMPRODUCT((TEXT('Income & Expense Tracker'!$A$5:$A$60,"yyyy-mm")=A15)*('Income & Expense Tracker'!$E$5:$E$60="Income")*'Income & Expense Tracker'!$F$5:$F$60) -> 0 | C15: =SUMPRODUCT((TEXT('Income & Expense Tracker'!$A$5:$A$60,"yyyy-mm")=A15)*('Income & Expense Tracker'!$E$5:$E$60="Expense")*'Income & Expense Tracker'!$F$5:$F$60) -> 0 | D15: =B15+C15 -> 0
A16: 2026-12 | B16: =SUMPRODUCT((TEXT('Income & Expense Tracker'!$A$5:$A$60,"yyyy-mm")=A16)*('Income & Expense Tracker'!$E$5:$E$60="Income")*'Income & Expense Tracker'!$F$5:$F$60) -> 0 | C16: =SUMPRODUCT((TEXT('Income & Expense Tracker'!$A$5:$A$60,"yyyy-mm")=A16)*('Income & Expense Tracker'!$E$5:$E$60="Expense")*'Income & Expense Tracker'!$F$5:$F$60) -> 0 | D16: =B16+C16 -> 0
A17: YTD TOTAL | B17: =SUM(B5:B16) -> 4250 | C17: =SUM(C5:C16) -> -186.4 | D17: =SUM(D5:D16) -> 4063.6
